BotAmino/BotAmino.py
BotAmino/__init__.py
botamino_new.py-3.0.dist-info/LICENSE
botamino_new.py-3.0.dist-info/METADATA
botamino_new.py-3.0.dist-info/WHEEL
botamino_new.py-3.0.dist-info/top_level.txt
botamino_new.py-3.0.dist-info/RECORD
