Metadata-Version: 2.1
Name: botamino-new.py
Version: 3.0
Summary: A library to create Amino bots.
Home-page: https://github.com/aminobot22/MAmino.py
Author: phoenix meliods
Author-email: parttimer57@gmail.com
License: MIT
Download-URL: https://github.com/aminobot22/MAmino.py.git
Keywords: aminoapps,amino_new-py,amino,amino-bot,narvii,api,python,python3,ThePhoenix78,AminoBot,BotAmino,botamino,aminobot,python3.x,slimakoi,official
Platform: UNKNOWN
Classifier: Programming Language :: Python :: 3
Classifier: License :: OSI Approved :: MIT License
Classifier: Operating System :: OS Independent
License-File: LICENSE
Requires-Dist: schedule
Requires-Dist: setuptools
Requires-Dist: requests
Requires-Dist: reportlab
Requires-Dist: websocket-client (==0.57.0)
Requires-Dist: argparse
Requires-Dist: amino-new.py
